py_valorant/__init__.py
py_valorant/api.py
py_valorant/cache.py
py_valorant/errors.py
py_valorant/main.py
py_valorant/utils.py
py_valorant/models/__init__.py
py_valorant/models/agents.py
py_valorant/models/buddies.py
py_valorant/models/bundles.py
py_valorant/models/ceremonies.py
py_valorant/models/competitivetiers.py
py_valorant/models/contenttiers.py
py_valorant/models/contracts.py
py_valorant/models/currencies.py
py_valorant/models/events.py
py_valorant/models/gamemodes.py
py_valorant/models/gears.py
py_valorant/models/levelborders.py
py_valorant/models/maps.py
py_valorant/models/playercards.py
py_valorant/models/playertitles.py
py_valorant/models/sprays.py
py_valorant/models/themes.py
py_valorant/models/weapons.py
py_valorant-1.0.2.dist-info/LICENSE
py_valorant-1.0.2.dist-info/METADATA
py_valorant-1.0.2.dist-info/WHEEL
py_valorant-1.0.2.dist-info/top_level.txt
py_valorant-1.0.2.dist-info/RECORD
