Metadata-Version: 2.1
Name: py-valorant
Version: 1.0.2
Summary: A Python Wrapper for valorant-api.com
Home-page: https://github.com/UnaPepsi/valorant-api-python
Author: Guimx
License: MIT
Keywords: valorant,api,valorant-api,valorant-api.com,py-valorant
Platform: UNKNOWN
Requires-Dist: requests
Requires-Dist: aiohttp
